pyutools/__init__.py
pyutools-0.0.0.dist-info/LICENSE
pyutools-0.0.0.dist-info/METADATA
pyutools-0.0.0.dist-info/WHEEL
pyutools-0.0.0.dist-info/top_level.txt
pyutools-0.0.0.dist-info/RECORD
